{
   "resourceType":"List",
   "id":"01111313-long",
   "text":{
      "status":"generated",
      "div":"List sample"
   },
   "status":"current",
   "mode":"changes",
   "date":"2018-02-21T12:17:00+11:00",
   "entry":[
      {
         "item":{
            "reference":"Patient/274"
         }
      },
      {
         "item":{
            "reference":"Patient/275"
         }
      },
      {
         "item":{
            "reference":"Patient/276"
         }
      },
      {
         "item":{
            "reference":"Patient/277"
         }
      },
      {
         "item":{
            "reference":"Patient/278"
         }
      },
      {
         "item":{
            "reference":"Patient/279"
         }
      },
      {
         "item":{
            "reference":"Patient/280"
         }
      },
      {
         "item":{
            "reference":"Patient/281"
         }
      },
      {
         "item":{
            "reference":"Patient/282"
         }
      },
      {
         "item":{
            "reference":"Patient/283"
         }
      },
      {
         "item":{
            "reference":"Patient/284"
         }
      },
      {
         "item":{
            "reference":"Patient/285"
         }
      },
      {
         "item":{
            "reference":"Patient/286"
         }
      },
      {
         "item":{
            "reference":"Patient/287"
         }
      },
      {
         "item":{
            "reference":"Patient/288"
         }
      },
      {
         "item":{
            "reference":"Patient/289"
         }
      },
      {
         "item":{
            "reference":"Patient/290"
         }
      },
      {
         "item":{
            "reference":"Patient/291"
         }
      },
      {
         "item":{
            "reference":"Patient/292"
         }
      },
      {
         "item":{
            "reference":"Patient/293"
         }
      },
      {
         "item":{
            "reference":"Patient/294"
         }
      },
      {
         "item":{
            "reference":"Patient/295"
         }
      },
      {
         "item":{
            "reference":"Patient/xcda"
         }
      },
      {
         "item":{
            "reference":"Patient/xds"
         }
      },
      {
         "item":{
            "reference":"Patient/animal"
         }
      },
      {
         "item":{
            "reference":"Patient/dicom"
         }
      },
      {
         "item":{
            "reference":"Patient/ihe-pcd"
         }
      },
      {
         "item":{
            "reference":"Patient/f001"
         }
      },
      {
         "item":{
            "reference":"Patient/f201"
         }
      },
      {
         "item":{
            "reference":"Patient/glossy"
         }
      },
      {
         "item":{
            "reference":"Patient/proband"
         }
      },
      {
         "item":{
            "reference":"Patient/genetics-example1"
         }
      },
      {
         "item":{
            "reference":"Patient/ch-example"
         }
      },
      {
         "item":{
            "reference":"Patient/newborn"
         }
      },
      {
         "item":{
            "reference":"Patient/mom"
         }
      }
   ],
   "meta":{
      "tag":[
         {
            "system":"http://terminology.hl7.org/CodeSystem/v3-ActReason",
            "code":"HTEST",
            "display":"test health data"
         }
      ]
   }
}